mongodb_toolkit/__init__.py
mongodb_toolkit/exceptions.py
mongodb_toolkit/execute_query.py
mongodb_toolkit/get_schema.py
mongodb_toolkit/models.py
mongodb_toolkit/toolkit.py
mongodb_toolkit/utils.py
mongodb_toolkit/validate_query_schema.py
mongodb_toolkit/validate_query_syntax.py
mongodb_toolkit-0.1.1.dist-info/licenses/LICENSE
mongodb_toolkit-0.1.1.dist-info/METADATA
mongodb_toolkit-0.1.1.dist-info/WHEEL
mongodb_toolkit-0.1.1.dist-info/top_level.txt
mongodb_toolkit-0.1.1.dist-info/RECORD
