Metadata-Version: 2.4
Name: MongoDB-toolkit
Version: 0.1.1
Summary: A Mongodb toolkit for Function Calling and AI Agents
Author-email: Ateeq Azam <contact@ateeq.pk>
License: CC BY-ND
Project-URL: Homepage, https://github.com/semwaqas/MongoDB-toolkit
Project-URL: Repository, https://github.com/semwaqas/MongoDB-toolkit
Keywords: AI Agents,Function Calling,Tool Calling,Mongodb,Toolkit,Langchain
License-File: LICENSE
Requires-Dist: pymongo
Requires-Dist: langchain
Dynamic: license-file
